{
  "taskId": "task-w2-forge-f2f3",
  "timestamp": "2026-02-17T20:39:00+08:00",
  "from": "kaiten-pulse",
  "to": "kaiten-forge",
  "priority": "critical",
  "track": "standard",
  "task": {
    "title": "Build OpenClaw Spawner + Message Proxy",
    "description": "Execute F2/F3: implement agent lifecycle spawner service and /api/agents/:id/chat proxy endpoint.",
    "deliverables": [
      "Spawner service (start/stop/status)",
      "Port allocation + profile generation",
      "Message proxy endpoint",
      "Basic tests for lifecycle + chat"
    ],
    "deadline": "2026-02-17T23:30:00+08:00",
    "references": [
      "~/ocaas-project/coordination/SYSTEM-REVIEW-2026-02-17.md",
      "~/ocaas-project/coordination/SHARED-CONTEXT.md"
    ]
  },
  "status": "completed"
}
